docspec_test/__init__.py
docspec_test/cli.py
docspec_test/plugin.py
docspec_test/runtime.py
docspec_test-0.1.6.dist-info/licenses/LICENSE
docspec_test_django/__init__.py
docspec_test_django/apps.py
docspec_test_django/management/commands/validate_doctests.py
docspec_test-0.1.6.dist-info/METADATA
docspec_test-0.1.6.dist-info/WHEEL
docspec_test-0.1.6.dist-info/entry_points.txt
docspec_test-0.1.6.dist-info/top_level.txt
docspec_test-0.1.6.dist-info/RECORD
