Metadata-Version: 2.4
Name: docspec_test
Version: 0.1.6
Summary: Pytest plugin for running docstring tests in Markdown blocks
Author: Alexandr Sukhryn
License-Expression: MIT
Project-URL: Homepage, https://github.com/alexsukhrin/docspec_test
Project-URL: Source, https://github.com/alexsukhrin/docspec_test
Project-URL: Tracker, https://github.com/alexsukhrin/docspec_test/issues
Keywords: pytest,plugin,doctest,docstring,markdown
Classifier: Development Status :: 3 - Alpha
Classifier: Programming Language :: Python
Classifier: Programming Language :: Python :: 3
Classifier: Programming Language :: Python :: 3 :: Only
Classifier: Programming Language :: Python :: 3.8
Classifier: Programming Language :: Python :: 3.9
Classifier: Programming Language :: Python :: 3.10
Classifier: Programming Language :: Python :: 3.11
Classifier: Programming Language :: Python :: 3.12
Classifier: Programming Language :: Python :: 3.13
Classifier: Framework :: Pytest
Classifier: Operating System :: OS Independent
Classifier: Topic :: Software Development :: Testing
Requires-Python: >=3.8
License-File: LICENSE
Requires-Dist: pytest>=7.0.0
Dynamic: license-file
